django_toolset
tests
