Metadata-Version: 1.1
Name: django-toolset
Version: 0.1.5
Summary: A set of helper functions and utilities for a Django application
Home-page: https://github.com/codezeus/django-toolset
Author: Dan Sackett
Author-email: danesackett@gmail.com
License: MIT License
Download-URL: https://github.com/codezeus/django-toolset/tarball/0.1.5
Platform: UNKNOWN
Classifier: Environment :: Web Environment
Classifier: Framework :: Django
Classifier: Framework :: Django :: 1.9
Classifier: Intended Audience :: Developers
Classifier: License :: OSI Approved :: MIT License
Classifier: Operating System :: OS Independent
Classifier: Programming Language :: Python
Classifier: Programming Language :: Python :: 2
Classifier: Programming Language :: Python :: 2.7
Classifier: Topic :: Utilities
